[
    {
        "_id": "Q101",
        "course": "RS101",
        "questionDesc": "Hi",
        "questionType": "RS101",
        "options": "May 17 at 11:59pm",
        "answer": 100
        
    },
    {
        "_id": "Q102",
        "course": "RS101",
        "questionDesc": "How",
        "questionType": "RS101",
        "options": "May 17 at 11:59pm",
        "answer": 100
        
    },
    {
        "_id": "Q103",
        "course": "RS101",
        "questionDesc": "are",
        "questionType": "RS101",
        "options": "May 17 at 11:59pm",
        "answer": 100
        
    },
    {
        "_id": "Q201",
        "course": "RS101",
        "questionDesc": "you",
        "questionType": "RS101",
        "options": "May 17 at 11:59pm",
        "answer": 100
        
    },
    {
        "_id": "Q202",
        "course": "RS101",
        "questionDesc": "im",
        "questionType": "RS101",
        "options": "May 17 at 11:59pm",
        "answer": 100
        
    },
    {
        "_id": "Q203",
        "course": "RS101",
        "questionDesc": "fine",
        "questionType": "RS101",
        "options": "May 17 at 11:59pm",
        "answer": 100
        
    },
    {
        "_id": "Q301",
        "course": "RS101",
        "questionDesc": "thank",
        "questionType": "RS101",
        "options": "May 17 at 11:59pm",
        "answer": 100
        
    },
    {
        "_id": "Q302",
        "course": "RS101",
        "questionDesc": "you",
        "questionType": "RS101",
        "options": "May 17 at 11:59pm",
        "answer": 100
        
    },
    {
        "_id": "Q303",
        "course": "RS101",
        "questionDesc": "!",
        "questionType": "RS101",
        "options": "May 17 at 11:59pm",
        "answer": 100
        
    }
]